{
  "account": "zgan3",
  "charfile": "runione",
  "charname": "runione",
  "generated": "2025-12-18 22:20:10",
  "char_stats": {
    "level": 1,
    "class": "Druid",
    "is_hc": false,
    "is_ladder": true,
    "progression": 0,
    "char_name_raw": "runione",
    "strength": 15,
    "energy": 20,
    "dexterity": 20,
    "vitality": 25,
    "unused_stats": 0,
    "unused_skills": 0,
    "current_hp": 55.0,
    "max_hp": 55.0,
    "current_mana": 20.0,
    "max_mana": 20.0,
    "current_stamina": 84.0,
    "max_stamina": 84.0,
    "experience": 0,
    "gold": 0,
    "stashed_gold": 32727
  },
  "unique_set": [],
  "runes": [],
  "rings": [],
  "belts": [],
  "amulets": [],
  "charms_small": [],
  "charms_large": [],
  "charms_grand": [],
  "weapons": [],
  "armors": [],
  "other": [
    "Lesser Healing Potion",
    "Lesser Healing Potion",
    "Lesser Healing Potion",
    "Lesser Healing Potion",
    "Town Portal Scroll",
    "Identify Scroll",
    "Lum Rune",
    "Lum Rune",
    "Io Rune",
    "Ort Rune",
    "Ko Rune",
    "Ko Rune",
    "Dol Rune",
    "Dol Rune",
    "Ith Rune",
    "Um Rune",
    "Hel Rune",
    "Nef Rune",
    "Amn Rune",
    "Amn Rune",
    "Eld Rune",
    "Ral Rune",
    "Hel Rune",
    "Eth Rune",
    "El Rune",
    "Ort Rune",
    "Eth Rune",
    "Nef Rune",
    "Ral Rune",
    "Eld Rune",
    "Io Rune",
    "Shael Rune",
    "Pul Rune",
    "Ith Rune",
    "Sol Rune",
    "Club",
    "Buckler"
  ]
}