{
  "account": "zliazubb",
  "charfile": "slabiruni",
  "charname": "slabiruni",
  "generated": "2025-12-18 22:20:10",
  "char_stats": {
    "level": 1,
    "class": "Assassin",
    "is_hc": false,
    "is_ladder": true,
    "progression": 0,
    "char_name_raw": "slabiruni",
    "strength": 20,
    "energy": 25,
    "dexterity": 20,
    "vitality": 20,
    "unused_stats": 0,
    "unused_skills": 0,
    "current_hp": 50.0,
    "max_hp": 50.0,
    "current_mana": 25.0,
    "max_mana": 25.0,
    "current_stamina": 95.0,
    "max_stamina": 95.0,
    "experience": 0,
    "gold": 0,
    "stashed_gold": 0
  },
  "unique_set": [],
  "runes": [],
  "rings": [],
  "belts": [],
  "amulets": [],
  "charms_small": [],
  "charms_large": [],
  "charms_grand": [],
  "weapons": [],
  "armors": [],
  "other": [
    "Lesser Healing Potion",
    "Lesser Healing Potion",
    "Lesser Healing Potion",
    "Lesser Healing Potion",
    "Lum Rune",
    "Lum Rune",
    "Lum Rune",
    "Ko Rune",
    "Io Rune",
    "Hel Rune",
    "Dol Rune",
    "Ko Rune",
    "Dol Rune",
    "Lum Rune",
    "Hel Rune",
    "Dol Rune",
    "Io Rune",
    "Lum Rune",
    "Ko Rune",
    "Hel Rune",
    "Dol Rune",
    "Ko Rune",
    "Dol Rune",
    "Dol Rune",
    "Hel Rune",
    "Ral Rune",
    "Tir Rune",
    "Tir Rune",
    "Io Rune",
    "Lum Rune",
    "Thul Rune",
    "Lum Rune",
    "Ral Rune",
    "Tal Rune",
    "Tir Rune",
    "Hel Rune",
    "Nef Rune",
    "Tir Rune",
    "Ith Rune",
    "Dol Rune",
    "Dol Rune",
    "Io Rune",
    "Dol Rune",
    "Shael Rune",
    "Sol Rune",
    "Shael Rune",
    "Shael Rune",
    "Amn Rune",
    "Amn Rune",
    "Thul Rune",
    "Ral Rune",
    "Eth Rune",
    "Io Rune",
    "Shael Rune",
    "Sol Rune",
    "Amn Rune",
    "Tal Rune",
    "Ort Rune",
    "Sol Rune",
    "Ral Rune",
    "Shael Rune",
    "Tal Rune",
    "Sol Rune",
    "Ral Rune",
    "Tal Rune",
    "Thul Rune",
    "Ort Rune",
    "Amn Rune",
    "Tir Rune",
    "Eth Rune",
    "Amn Rune",
    "Tal Rune",
    "Ral Rune",
    "Ort Rune",
    "Ral Rune",
    "Eth Rune",
    "Ral Rune",
    "Ral Rune",
    "Ral Rune",
    "Eth Rune",
    "Thul Rune",
    "Dol Rune",
    "Ort Rune",
    "Katar",
    "Buckler"
  ]
}